gadasyncblock/__init__.py
gadasyncblock-0.0.2.dist-info/LICENSE
gadasyncblock-0.0.2.dist-info/METADATA
gadasyncblock-0.0.2.dist-info/WHEEL
gadasyncblock-0.0.2.dist-info/top_level.txt
gadasyncblock-0.0.2.dist-info/RECORD
