Metadata-Version: 2.1
Name: gadasyncblock
Version: 0.0.2
Summary: Event loop lock detector for Python
Home-page: https://github.com/AlexDemure/gadasyncblock
Author: Alexander Grishchenko
Author-email: alexanderdemure@gmail.com
Classifier: Programming Language :: Python :: 3
Classifier: License :: OSI Approved :: MIT License
Classifier: Operating System :: OS Independent
Requires-Python: >=3.8
License-File: LICENSE
